simple_strop/__init__.py
simple_strop/operations.py
simple_strop/test_operations.py
simple_strop/test_utils.py
simple_strop/utils.py
simple_strop-1.0.2.dist-info/LICENSE
simple_strop-1.0.2.dist-info/METADATA
simple_strop-1.0.2.dist-info/WHEEL
simple_strop-1.0.2.dist-info/top_level.txt
simple_strop-1.0.2.dist-info/RECORD
