Metadata-Version: 2.1
Name: simple-strop
Version: 1.0.2
Summary: A simple python package to demo CI/CD pipelines
Home-page: https://gitlab.com/pipeline-demos/simple-python-package
Author: Jarod Latta
Author-email: jarod@visimo.ai
License: UNKNOWN
Platform: UNKNOWN
Classifier: Programming Language :: Python :: 3
Classifier: License :: OSI Approved :: MIT License
Classifier: Operating System :: OS Independent
Requires-Python: >=3.8
